raccoon_scanner-0.8.5.dist-info/METADATA
raccoon_scanner-0.8.5.dist-info/RECORD
raccoon_scanner-0.8.5.dist-info/WHEEL
raccoon_scanner-0.8.5.dist-info/entry_points.txt
raccoon_scanner-0.8.5.dist-info/top_level.txt
raccoon_src/__init__.py
raccoon_src/main.py
raccoon_src/lib/__init__.py
raccoon_src/lib/dns_handler.py
raccoon_src/lib/fuzzer.py
raccoon_src/lib/host.py
raccoon_src/lib/owasp.py
raccoon_src/lib/scanner.py
raccoon_src/lib/storage_explorer.py
raccoon_src/lib/sub_domain.py
raccoon_src/lib/tls.py
raccoon_src/lib/waf.py
raccoon_src/lib/web_app.py
raccoon_src/utils/__init__.py
raccoon_src/utils/coloring.py
raccoon_src/utils/exceptions.py
raccoon_src/utils/help_utils.py
raccoon_src/utils/logger.py
raccoon_src/utils/request_handler.py
raccoon_src/utils/singleton.py
raccoon_src/utils/web_server_validator.py
raccoon_src/wordlists/fuzzlist
raccoon_src/wordlists/storage_sensitive
raccoon_src/wordlists/subdomains
tests/__init__.py
tests/test_fuzzer.py
tests/test_host.py
tests/test_subdomain.py
tests/test_waf.py
tests/test_web_app.py
