Metadata-Version: 2.1
Name: raccoon-scanner
Version: 0.8.5
Summary: Offensive Security Tool for Reconnaissance and Information Gathering
Home-page: https://github.com/evyatarmeged/Raccoon
Author: Evyatar Meged
Author-email: evyatarmeged@gmail.com
License: MIT
Platform: UNKNOWN
Requires-Dist: beautifulsoup4
Requires-Dist: requests
Requires-Dist: dnspython
Requires-Dist: lxml
Requires-Dist: click
Requires-Dist: fake-useragent
Requires-Dist: requests[socks]
Requires-Dist: xmltodict
